graphMeasures/__init__.py
graphMeasures/additional_features.py
graphMeasures/cpp_comparison.py
graphMeasures/features_for_any_graph.py
graphMeasures/loggers.py
graphMeasures/List-of-Lists-main/__init__.py
graphMeasures/List-of-Lists-main/lol_graph.py
graphMeasures/List-of-Lists-main/lol_graph_directed.py
graphMeasures/edges_features/__init__.py
graphMeasures/edges_features/feature_calculator.py
graphMeasures/edges_features/pickle_manager.py
graphMeasures/edges_features/acc_features/__init__.py
graphMeasures/edges_features/acc_features/acc_utils.py
graphMeasures/edges_features/acc_features/graph_converter.py
graphMeasures/edges_features/acc_features/motifs.py
graphMeasures/edges_features/motif_variations/3_directed.pkl
graphMeasures/edges_features/motif_variations/3_undirected.pkl
graphMeasures/edges_features/motif_variations/4_directed.pkl
graphMeasures/edges_features/motif_variations/4_undirected.pkl
graphMeasures/edges_features/motif_variations/__init__.py
graphMeasures/edges_features/motif_variations/isomorphic.py
graphMeasures/edges_features/motif_variations/rewrite_variations.py
graphMeasures/features_algorithms/__init__.py
graphMeasures/features_algorithms/accelerated_graph_features/__init__.py
graphMeasures/features_algorithms/accelerated_graph_features/attractor_basin.py
graphMeasures/features_algorithms/accelerated_graph_features/bfs_moments.py
graphMeasures/features_algorithms/accelerated_graph_features/flow.py
graphMeasures/features_algorithms/accelerated_graph_features/k_core.py
graphMeasures/features_algorithms/accelerated_graph_features/motifs.py
graphMeasures/features_algorithms/accelerated_graph_features/page_rank.py
graphMeasures/features_algorithms/accelerated_graph_features/src/__init__.py
graphMeasures/features_algorithms/accelerated_graph_features/src/accelerated_graph_features/__init__.py
graphMeasures/features_algorithms/accelerated_graph_features/src/accelerated_graph_features/feature_benchmarks.py
graph_measures-0.1.57.dist-info/METADATA
graph_measures-0.1.57.dist-info/WHEEL
graph_measures-0.1.57.dist-info/top_level.txt
graph_measures-0.1.57.dist-info/RECORD
