Metadata-Version: 2.1
Name: graph-measures
Version: 0.1.57
Summary: A python package for calculating topological graph features on cpu/gpu
Home-page: https://github.com/louzounlab/graph-measures
Author: Itay Levinas
Maintainer: Ziv Naim
Maintainer-email: zivnaim3@gmail.com
License: GPL
Keywords: gpu,graph,topological-features-calculator
Classifier: Programming Language :: Python
Classifier: Programming Language :: C++
Classifier: Operating System :: Unix
Classifier: Operating System :: POSIX :: Linux
Requires-Python: >=3.6.8
Requires-Dist: setuptools
Requires-Dist: networkx (==2.6.3)
Requires-Dist: pandas
Requires-Dist: numpy
Requires-Dist: matplotlib
Requires-Dist: scipy
Requires-Dist: scikit-learn
Requires-Dist: python-louvain
Requires-Dist: bitstring
Requires-Dist: future
Requires-Dist: torch
